google_play_reviews_scraper/__init__.py
google_play_reviews_scraper/app.py
google_play_reviews_scraper-0.1.2.dist-info/METADATA
google_play_reviews_scraper-0.1.2.dist-info/WHEEL
google_play_reviews_scraper-0.1.2.dist-info/entry_points.txt
google_play_reviews_scraper-0.1.2.dist-info/top_level.txt
google_play_reviews_scraper-0.1.2.dist-info/RECORD
